<?xml version="1.0" encoding="UTF-8" standalone="no"?>
<Graph>
    <Nodes>
        <Node index="0" posX="76.0" posY="127.0" type="2" x="1" y="1"/>
        <Node index="1" posX="382.0" posY="127.0" type="0" x="7" y="1"/>
        <Node index="2" posX="76.0" posY="331.0" type="0" x="1" y="5"/>
        <Node index="3" posX="382.0" posY="331.0" type="0" x="7" y="5"/>
        <Node index="4" posX="76.0" posY="433.0" type="0" x="1" y="7"/>
        <Node index="5" posX="382.0" posY="433.0" type="0" x="7" y="7"/>
    </Nodes>
    <Edges>
        <Edge end="1" start="0" type="0"/>
        <Edge end="3" start="1" type="0"/>
        <Edge end="2" start="0" type="0"/>
        <Edge end="4" start="2" type="0"/>
        <Edge end="5" start="4" type="0"/>
        <Edge end="3" start="5" type="0"/>
    </Edges>
</Graph>